ensemble/__init__.py
ensemble/defaults.py
ensemble/heartbeat.py
ensemble/metrics.py
ensemble/schema.py
ensemble/server.py
ensemble/utils.py
ensemble/client/__init__.py
ensemble/client/run.py
ensemble/config/__init__.py
ensemble/config/config.py
ensemble/config/types.py
ensemble/logger/__init__.py
ensemble/logger/generate.py
ensemble/logger/logger.py
ensemble/members/README.md
ensemble/members/__init__.py
ensemble/members/auth.py
ensemble/members/base.py
ensemble/members/client.py
ensemble/members/metrics.py
ensemble/members/flux/__init__.py
ensemble/members/flux/__main__.py
ensemble/members/flux/metrics.py
ensemble/members/flux/minicluster.py
ensemble/members/flux/queue.py
ensemble/protos/ensemble_service_pb2.py
ensemble/protos/ensemble_service_pb2.pyi
ensemble/protos/ensemble_service_pb2_grpc.py
ensemble_python-0.0.16.dist-info/LICENSE
ensemble_python-0.0.16.dist-info/METADATA
ensemble_python-0.0.16.dist-info/NOTICE
ensemble_python-0.0.16.dist-info/WHEEL
ensemble_python-0.0.16.dist-info/entry_points.txt
ensemble_python-0.0.16.dist-info/top_level.txt
ensemble_python-0.0.16.dist-info/RECORD
