Metadata-Version: 2.1
Name: ensemble-python
Version: 0.0.16
Summary: Ensemble orchestrator for queue orchestration
Home-page: https://github.com/converged-computing/ensemble-python
Author: Vanessasaurus
Author-email: vsoch@users.noreply.github.com
Maintainer: Vanessasaurus
License: MIT
Keywords: multi-cluster,scheduler
Classifier: Intended Audience :: Science/Research
Classifier: Intended Audience :: Developers
Classifier: License :: OSI Approved :: Apache Software License
Classifier: Programming Language :: C
Classifier: Programming Language :: Python
Classifier: Topic :: Software Development
Classifier: Topic :: Scientific/Engineering
Classifier: Operating System :: Unix
Classifier: Programming Language :: Python :: 3.8
License-File: LICENSE
License-File: NOTICE
Requires-Dist: grpcio
Requires-Dist: grpcio-tools
Requires-Dist: jsonschema
Requires-Dist: pyyaml
Requires-Dist: jobspec
Requires-Dist: river
Requires-Dist: kubernetes
